n26/__init__.py
n26/__main__.py
n26/api.py
n26/cli.py
n26/config.py
n26/const.py
n26/util.py
n26-3.3.1.dist-info/LICENSE
n26-3.3.1.dist-info/METADATA
n26-3.3.1.dist-info/WHEEL
n26-3.3.1.dist-info/entry_points.txt
n26-3.3.1.dist-info/top_level.txt
n26-3.3.1.dist-info/RECORD
